raftel/__init__.py
raftel/raftel.py
raftel-0.4.0.dist-info/WHEEL
raftel-0.4.0.dist-info/METADATA
raftel-0.4.0.dist-info/RECORD
