Metadata-Version: 2.1
Name: raftel
Version: 0.4.0
Summary: the easiest way to plot s2id
Home-page: https://github.com/mitbal/raftel
License: MIT
Keywords: s2id,map,geography,visualization
Author: M Iqbal Tawakal
Author-email: mit.iqi@gmail.com
Requires-Python: >=3.9
Classifier: License :: OSI Approved :: MIT License
Classifier: Programming Language :: Python :: 3
Classifier: Programming Language :: Python :: 3.9
Requires-Dist: monochromap (>=0.3.0)
Requires-Dist: s2sphere (>=0.2.5)
Requires-Dist: seaborn (>=0.11.1)
Requires-Dist: staticmap (>=0.5.5)
Project-URL: Repository, https://github.com/mitbal/raftel
